Metadata-Version: 2.1
Name: types-confluent-kafka-fork
Version: 1.2.3
Summary: 
Home-page: https://github.com/kowalskithomas/types-confluent-kafka
License: Apache-2.0 license
Keywords: types,typings,stubs,confluent_kafka,mypy,lsp,completion,type hints,type checking
Author: Thomas Kowalski
Author-email: thom.kowa@gmail.com
Requires-Python: >=3.9,<=3.13
Classifier: Development Status :: 4 - Beta
Classifier: Intended Audience :: Developers
Classifier: License :: OSI Approved :: Apache Software License
Classifier: License :: Other/Proprietary License
Classifier: Operating System :: OS Independent
Classifier: Programming Language :: Python
Classifier: Programming Language :: Python :: 3
Classifier: Programming Language :: Python :: 3.9
Classifier: Programming Language :: Python :: 3.10
Classifier: Programming Language :: Python :: 3.11
Classifier: Programming Language :: Python :: 3.12
Classifier: Programming Language :: Python :: 3.13
Classifier: Topic :: Software Development
Classifier: Topic :: Software Development :: Libraries
Classifier: Topic :: Software Development :: Libraries :: Python Modules
Project-URL: Repository, https://github.com/kowalskithomas/types-confluent-kafka
